week10/ex2_full_adder/full.v
module full
  (
   bit1,
   bit2,
   Icarry,
   sum,
   Ocarry
   );
 
  input  bit1;
  input  bit2;
  input  Icarry;
  output sum;
  output Ocarry;
 
  wire   W1;
  wire   W2;
  wire   W3;
       
  assign W1 = bit1 ^ bit2;
  assign W2 = W1 & Icarry;
  assign W3 = bit1 & bit2;
 
  assign sum   = W1 ^ Icarry;
  assign Ocarry = W2 | W3;
   
endmodule

week10/ex2_full_adder/testbench.v
module testbench;

// input and output test signals
reg a, b, carry_in;

wire carry_out, sum;

// creating the instance of the module we want to test
full fa(a, b, carry_in, sum, carry_out);

initial
begin
a = 1'b0;
b = 1'b1;
carry_in = 1'b0;
#5; // pause (5 units of delay )
carry_in = 1'b1;
#5;
a = 1'b1;
b = 1'b0;
#5;
carry_in = 1'b0;
#5
a = 1'b0;
b = 1'b0;
#5
carry_in = 1'b1;
#5
a = 1'b1;
b = 1'b1;
#5;
carry_in = 1'b0;
end

// print signal values on every change
initial
$monitor("a= %b b = %b carry_in = %b sum = %b carry_out = %b", a, b, carry_in, sum, carry_out);

initial
$dumpvars;

endmodule

week10/ex2_full_adder/simulation/modelsim/dump.vcd
$date
	Fri Nov 06 00:11:46 2020
$end
$version
	ModelSim Version 10.5b
$end
$timescale
	1ps
$end

$scope module testbench $end
$var reg 1 ! a $end
$var reg 1 " b $end
$var reg 1 # carry_in $end
$var wire 1 $ carry_out $end
$var wire 1 % sum $end

$scope module fa $end
$var wire 1 & bit1 $end
$var wire 1 ' bit2 $end
$var wire 1 ( Icarry $end
$var wire 1 % sum $end
$var wire 1 $ Ocarry $end
$var wire 1 ) W1 $end
$var wire 1 * W2 $end
$var wire 1 + W3 $end
$upscope $end
$upscope $end
$enddefinitions $end
#0
$dumpvars
0!
1"
0#
0$
1%
1)
0*
0+
0(
1'
0&
$end
#5
1#
1(
1*
0%
1$
#10
1!
0"
1&
0'
#15
0#
0(
0*
1%
0$
#20
0!
0&
0)
0%
#25
1#
1(
1%
#30
1!
1"
1&
1'
1+
1$
#35
0#
0(
0%
